disguisedata/__init__.py
disguisedata/disguisedata.py
disguisedata-1.0.4.dist-info/LICENSE.txt
disguisedata-1.0.4.dist-info/METADATA
disguisedata-1.0.4.dist-info/WHEEL
disguisedata-1.0.4.dist-info/top_level.txt
disguisedata-1.0.4.dist-info/RECORD
