Metadata-Version: 2.1
Name: disguisedata
Version: 1.0.4
Summary: A tiny tool for generating synthetic data from the original one
Author: Deniz Dahman's, Ph.D.
Author-email: dahmansphi@gmail.com
Project-URL: Source, https://github.com/dahmansphi/disguisedata
Project-URL: Project, https://dahmansphi.com/disguisedata
Keywords: Cybersecurity,Machine Learning,Artificial Intelligence,Synthetic Data
Classifier: Development Status :: 3 - Alpha
Classifier: Intended Audience :: Developers
Classifier: Topic :: Software Development :: Build Tools
Classifier: License :: OSI Approved :: MIT License
Classifier: Programming Language :: Python :: 3
Requires-Python: >=3.9
License-File: LICENSE.txt
